packagedb/__init__.py
packagedb/api.py
packagedb/api_custom.py
packagedb/models.py
packagedb/serializers.py
packagedb/signals.py
packagedb/migrations/0001_initial.py
packagedb/migrations/0002_auto_20160707_1018.py
packagedb/migrations/0003_auto_20160708_1513.py
packagedb/migrations/0004_auto_20160713_0022.py
packagedb/migrations/0005_auto_20170217_0309.py
packagedb/migrations/0006_package_mining_level.py
packagedb/migrations/0007_auto_20180713_0144.py
packagedb/migrations/0008_package_package_url.py
packagedb/migrations/0009_auto_20180918_1225.py
packagedb/migrations/0010_auto_20180919_1740.py
packagedb/migrations/0011_auto_20180921_1129.py
packagedb/migrations/0012_auto_20181001_1120.py
packagedb/migrations/0013_auto_20181001_1209.py
packagedb/migrations/0014_remove_package_package_url.py
packagedb/migrations/0015_remove_package_download_checksums.py
packagedb/migrations/0016_auto_20181023_1211.py
packagedb/migrations/0017_auto_20181023_1211.py
packagedb/migrations/0018_auto_20181023_1212.py
packagedb/migrations/0019_auto_20181023_1212.py
packagedb/migrations/0020_package_download_sha256.py
packagedb/migrations/0021_package_download_sha512.py
packagedb/migrations/0022_package_manifest_path.py
packagedb/migrations/0023_package_source_packages.py
packagedb/migrations/0024_auto_20181030_1817.py
packagedb/migrations/0025_auto_20181030_1817.py
packagedb/migrations/0026_auto_20181030_1824.py
packagedb/migrations/0027_auto_20181030_1825.py
packagedb/migrations/0028_auto_20181127_0224.py
packagedb/migrations/0029_auto_20181127_0246.py
packagedb/migrations/0030_auto_20190107_1616.py
packagedb/migrations/0031_auto_20190110_2354.py
packagedb/migrations/0032_auto_20190125_0019.py
packagedb/migrations/0033_auto_20190128_2056.py
packagedb/migrations/0034_auto_20200407_2232.py
packagedb/migrations/0035_auto_20200408_2126.py
packagedb/migrations/0036_auto_20200416_2131.py
packagedb/migrations/0037_auto_20200423_1242.py
packagedb/migrations/0038_add_index_for_filter_fields.py
packagedb-2.0.0.dist-info/AUTHORS.rst
packagedb-2.0.0.dist-info/CHANGELOG.rst
packagedb-2.0.0.dist-info/METADATA
packagedb-2.0.0.dist-info/NOTICE
packagedb-2.0.0.dist-info/README.rst
packagedb-2.0.0.dist-info/WHEEL
packagedb-2.0.0.dist-info/apache-2.0.LICENSE
packagedb-2.0.0.dist-info/cc-by-sa-4.0.LICENSE
packagedb-2.0.0.dist-info/top_level.txt
packagedb-2.0.0.dist-info/RECORD
